baicai_base/__init__.py
baicai_base/agents/graphs/__init__.py
baicai_base/agents/graphs/base_graph.py
baicai_base/agents/graphs/nodes/__init__.py
baicai_base/agents/graphs/nodes/base_coder_node.py
baicai_base/agents/graphs/nodes/base_node.py
baicai_base/agents/graphs/nodes/debugger_node.py
baicai_base/agents/graphs/nodes/helper_node.py
baicai_base/agents/graphs/nodes/run_code_node.py
baicai_base/agents/graphs/react_coder_graph.py
baicai_base/agents/graphs/state.py
baicai_base/agents/roles/__init__.py
baicai_base/agents/roles/coder.py
baicai_base/agents/roles/debugger.py
baicai_base/agents/roles/helper.py
baicai_base/configs/__init__.py
baicai_base/configs/config_manager.py
baicai_base/configs/llm_config.py
baicai_base/services/__init__.py
baicai_base/services/llms.py
baicai_base/utils/__init__.py
baicai_base/utils/code/__init__.py
baicai_base/utils/code/execute.py
baicai_base/utils/code/utils.py
baicai_base/utils/constants/__init__.py
baicai_base/utils/constants/common_prompts.py
baicai_base/utils/constants/error_messages.py
baicai_base/utils/data/__init__.py
baicai_base/utils/data/code_types.py
baicai_base/utils/data/constants.py
baicai_base/utils/data/extraction.py
baicai_base/utils/data/loaders.py
baicai_base/utils/data/preprocess.py
baicai_base/utils/data/preview.py
baicai_base/utils/data/storage.py
baicai_base/utils/data/types.py
baicai_base/utils/profile.py
baicai_base/utils/setups/__init__.py
baicai_base/utils/setups/setup_logging.py
baicai_base/utils/setups/setups.py
baicai_base-0.1.2.dist-info/LICENSE
baicai_base-0.1.2.dist-info/METADATA
baicai_base-0.1.2.dist-info/WHEEL
baicai_base-0.1.2.dist-info/RECORD
