Metadata-Version: 2.3
Name: baicai-base
Version: 0.1.2
Summary: Base package for Baicai development and tutor
License: MIT
Keywords: python,agent,AI,machine learning,LLM
Author: Zhaoyang tech
Author-email: gengyabc@aliyun.com
Requires-Python: >=3.10,<3.12
Classifier: Development Status :: 4 - Beta
Classifier: Intended Audience :: Developers
Classifier: Intended Audience :: Education
Classifier: License :: OSI Approved :: MIT License
Classifier: Operating System :: OS Independent
Classifier: Programming Language :: Python :: 3
Classifier: Programming Language :: Python :: 3.10
Classifier: Programming Language :: Python :: 3.11
Classifier: Topic :: Scientific/Engineering :: Artificial Intelligence
Classifier: Topic :: Software Development :: Libraries :: Python Modules
Requires-Dist: grandalf (>=0.8,<0.9)
Requires-Dist: json-repair (>=0.44.1,<0.45.0)
Requires-Dist: jupyter (>=1.1.1,<2.0.0)
Requires-Dist: langchain (==0.3.24)
Requires-Dist: langchain-core (==0.3.57)
Requires-Dist: langchain-groq (>=0.2.3,<1.0)
Requires-Dist: langchain-openai (>=0.3.2,<1.0)
Requires-Dist: langgraph (==0.4.1)
Requires-Dist: langgraph-checkpoint (==2.0.25)
Requires-Dist: langgraph-prebuilt (==0.1.8)
Requires-Dist: langgraph-sdk (==0.1.66)
Requires-Dist: lxml (>=5.4.0,<6.0.0)
Requires-Dist: openpyxl (>=3.1.5,<4.0.0)
Requires-Dist: pandas (>=2.2.3,<3.0.0)
Requires-Dist: python-dotenv (>=1.0.0,<2.0.0)
Requires-Dist: rich (>=13.7.0,<14.0.0)
